specflow/__init__.py
specflow/core/__init__.py
specflow/core/compositions.py
specflow/core/conditions.py
specflow/core/exceptions.py
specflow/core/schema.py
specflow/core/types/__init__.py
specflow/core/types/array.py
specflow/core/types/boolean.py
specflow/core/types/constraints.py
specflow/core/types/integer.py
specflow/core/types/number.py
specflow/core/types/string.py
specflow/core/types/type.py
specflow/field.py
specflow/py.typed
specflow/typing.py
specflow-1.0.0.dist-info/WHEEL
specflow-1.0.0.dist-info/entry_points.txt
specflow-1.0.0.dist-info/METADATA
specflow-1.0.0.dist-info/RECORD
