Metadata-Version: 2.4
Name: specflow
Version: 1.0.0
Summary: A Python library for JSON Schema validation with a fluent, type-safe API
Keywords: json-schema,validation,schema,json,type-checking
Author: Pedro José Mora Gallegos
Author-email: Pedro José Mora Gallegos <pedrojosemoragallegos@outlook.de>
License-Expression: MIT
Classifier: Development Status :: 5 - Production/Stable
Classifier: Intended Audience :: Developers
Classifier: License :: OSI Approved :: MIT License
Classifier: Programming Language :: Python :: 3
Classifier: Programming Language :: Python :: 3.10
Classifier: Programming Language :: Python :: 3.11
Classifier: Programming Language :: Python :: 3.12
Classifier: Programming Language :: Python :: 3.13
Classifier: Topic :: Software Development :: Libraries :: Python Modules
Classifier: Topic :: Software Development :: Quality Assurance
Classifier: Typing :: Typed
Requires-Python: >=3.10
Project-URL: Homepage, https://github.com/pedrojosemoragallegos/specflow
Project-URL: Repository, https://github.com/pedrojosemoragallegos/specflow
